magnelPy/AIC.py
magnelPy/LHS.py
magnelPy/__init__.py
magnelPy/admin.py
magnelPy/developer.py
magnelPy/openfig.py
magnelPy/ploty_mcplotface.py
magnelPy/sampling.py
magnelPy/statFunc.py
magnelPy/stochVar.py
magnelPy/Abaqus/AbaqusPropertiesMaster.py
magnelPy/Abaqus/Abaqus_test_graphs.py
magnelPy/Abaqus/MechanicalProperties.py
magnelPy/Abaqus/ThermalProperties.py
magnelPy/Abaqus/__init__.py
magnelPy/ML/__init__.py
magnelPy/ML/regression.py
magnelPy/SAFIRshell/Thermal.py
magnelPy/SAFIRshell/__init__.py
magnelPy/SAFIRshell/control.py
magnelPy/SAFIRshell/postprocess.py
magnelPy/SFE/FireCurve.py
magnelPy/SFE/MechanicalTools.py
magnelPy/SFE/Radiation.py
magnelPy/SFE/ThermalTools.py
magnelPy/SFE/__init__.py
magnelPy/SFE/Capacity/EC3.py
magnelPy/SFE/Capacity/__init__.py
magnelPy/SFE/MaterialProperties/Air.py
magnelPy/SFE/MaterialProperties/Concrete.py
magnelPy/SFE/MaterialProperties/SFRM.py
magnelPy/SFE/MaterialProperties/Steel.py
magnelPy/SFE/MaterialProperties/UserDefined.py
magnelPy/SFE/MaterialProperties/__init__.py
magnelPy-0.3.2.dist-info/LICENSE
magnelPy-0.3.2.dist-info/METADATA
magnelPy-0.3.2.dist-info/WHEEL
magnelPy-0.3.2.dist-info/top_level.txt
magnelPy-0.3.2.dist-info/RECORD
