Metadata-Version: 2.1
Name: magnelPy
Version: 0.3.2
Summary: Python toolbox of the Structural Fire Engineering team of Ghent University (SFE@UGent)
Home-page: https://github.ugent.be/MagnelPy/MagnelPy
Author: magnelPy
Author-email: ruben.vancoile@ugent.be
Classifier: Programming Language :: Python :: 3
Classifier: License :: OSI Approved :: MIT License
Classifier: Operating System :: OS Independent
License-File: LICENSE
